actions_toolkit/__init__.py
actions_toolkit/cache.py
actions_toolkit/cache_utils.py
actions_toolkit/command.py
actions_toolkit/core.py
actions_toolkit/file_command.py
actions_toolkit/github.py
actions_toolkit/io_utils.py
actions_toolkit/oidc_utils.py
actions_toolkit/utils.py
tests/__init__.py
tests/test_core.py
tests/test_github.py
actions_toolkit-0.1.15.dist-info/LICENSE
actions_toolkit-0.1.15.dist-info/METADATA
actions_toolkit-0.1.15.dist-info/WHEEL
actions_toolkit-0.1.15.dist-info/top_level.txt
actions_toolkit-0.1.15.dist-info/RECORD
