Metadata-Version: 2.1
Name: actions-toolkit
Version: 0.1.15
Summary: 🛠 The GitHub ToolKit for developing GitHub Actions in Python.
Home-page: https://github.com/yanglbme/actions-toolkit
Author: yanglbme
Author-email: contact@yanglibin.info
License: MIT
Classifier: Programming Language :: Python :: 3.6
Classifier: Programming Language :: Python :: 3.7
Classifier: Programming Language :: Python :: 3.8
Classifier: Programming Language :: Python :: 3.9
Classifier: Programming Language :: Python :: 3.10
Classifier: License :: OSI Approved :: MIT License
Classifier: Operating System :: OS Independent
Requires-Python: >=3.6
License-File: LICENSE
